querit/__init__.py
querit/client.py
querit/errors.py
querit/version.py
querit/models/request.py
querit/models/response.py
querit/utils/__init__.py
querit/utils/enums.py
querit/utils/http.py
querit-0.1.2.dist-info/licenses/LICENSE
querit-0.1.2.dist-info/METADATA
querit-0.1.2.dist-info/WHEEL
querit-0.1.2.dist-info/top_level.txt
querit-0.1.2.dist-info/RECORD
