Metadata-Version: 2.4
Name: querit
Version: 0.1.2
Summary: Querit Python SDK
License:                                  Apache License
Keywords: search,sdk,querit,querit-python
Classifier: Programming Language :: Python :: 3
Classifier: License :: OSI Approved :: Apache Software License
Classifier: Operating System :: OS Independent
Requires-Python: >=3.8
License-File: LICENSE
Requires-Dist: requests
Dynamic: license-file
